musify/__init__.py
musify/report.py
musify/local/__init__.py
musify/local/base.py
musify/local/collection.py
musify/local/exception.py
musify/local/file.py
musify/local/library/__init__.py
musify/local/library/library.py
musify/local/library/musicbee.py
musify/local/playlist/__init__.py
musify/local/playlist/base.py
musify/local/playlist/m3u.py
musify/local/playlist/utils.py
musify/local/playlist/xautopf.py
musify/local/track/__init__.py
musify/local/track/field.py
musify/local/track/flac.py
musify/local/track/m4a.py
musify/local/track/mp3.py
musify/local/track/utils.py
musify/local/track/wma.py
musify/local/track/base/__init__.py
musify/local/track/base/reader.py
musify/local/track/base/track.py
musify/local/track/base/writer.py
musify/processors/__init__.py
musify/processors/base.py
musify/processors/compare.py
musify/processors/download.py
musify/processors/exception.py
musify/processors/filter.py
musify/processors/filter_matcher.py
musify/processors/limit.py
musify/processors/match.py
musify/processors/sort.py
musify/processors/time.py
musify/shared/__init__.py
musify/shared/exception.py
musify/shared/field.py
musify/shared/handlers.py
musify/shared/logger.py
musify/shared/types.py
musify/shared/utils.py
musify/shared/api/__init__.py
musify/shared/api/authorise.py
musify/shared/api/exception.py
musify/shared/api/request.py
musify/shared/core/__init__.py
musify/shared/core/base.py
musify/shared/core/collection.py
musify/shared/core/enum.py
musify/shared/core/misc.py
musify/shared/core/object.py
musify/shared/remote/__init__.py
musify/shared/remote/_base.py
musify/shared/remote/api.py
musify/shared/remote/base.py
musify/shared/remote/config.py
musify/shared/remote/enum.py
musify/shared/remote/exception.py
musify/shared/remote/library.py
musify/shared/remote/object.py
musify/shared/remote/types.py
musify/shared/remote/processors/__init__.py
musify/shared/remote/processors/check.py
musify/shared/remote/processors/search.py
musify/shared/remote/processors/wrangle.py
musify-2024.1.6.dist-info/METADATA
musify-2024.1.6.dist-info/WHEEL
musify-2024.1.6.dist-info/licenses/LICENSE
musify-2024.1.6.dist-info/RECORD
