Metadata-Version: 2.1
Name: musify
Version: 2024.1.6
Summary: Synchronise your music library to local or remote libraries
Project-URL: Documentation, https://geo-martino.github.io/musify/
Project-URL: Source code, https://github.com/geo-martino/musify
Project-URL: Issues, https://github.com/geo-martino/musify/issues
Author-email: George Martin Marino <gm.engineer+musify@pm.me>
License-File: LICENSE
Classifier: Development Status :: 2 - Pre-Alpha
Classifier: Intended Audience :: Developers
Classifier: Intended Audience :: End Users/Desktop
Classifier: License :: OSI Approved :: GNU Affero General Public License v3
Classifier: Natural Language :: English
Classifier: Operating System :: MacOS :: MacOS X
Classifier: Operating System :: Microsoft :: Windows
Classifier: Operating System :: POSIX :: Linux
Classifier: Programming Language :: Python :: 3.12
Requires-Python: >=3.12
Requires-Dist: lxml~=5.1
Requires-Dist: mutagen~=1.47
Requires-Dist: pillow~=10.1
Requires-Dist: python-dateutil~=2.8.2
Requires-Dist: pyyaml~=6.0
Requires-Dist: requests-cache~=1.1
Requires-Dist: requests~=2.31
Requires-Dist: tqdm~=4.66
Requires-Dist: xmltodict~=0.13
Provides-Extra: dev
Requires-Dist: flake8; extra == 'dev'
Requires-Dist: grip~=4.6; extra == 'dev'
Requires-Dist: musify[docs,test]; extra == 'dev'
Provides-Extra: docs
Requires-Dist: autodocsumm~=0.2; extra == 'docs'
Requires-Dist: graphviz~=0.20; extra == 'docs'
Requires-Dist: renku-sphinx-theme; extra == 'docs'
Requires-Dist: sphinx-autodoc-typehints~=1.25; extra == 'docs'
Requires-Dist: sphinx~=7.2; extra == 'docs'
Provides-Extra: test
Requires-Dist: pycountry~=23.12; extra == 'test'
Requires-Dist: pytest-lazy-fixture~=0.6; extra == 'test'
Requires-Dist: pytest-mock~=3.12; extra == 'test'
Requires-Dist: pytest-repeat~=0.9; extra == 'test'
Requires-Dist: pytest~=7.4; extra == 'test'
Requires-Dist: requests-mock~=1.11; extra == 'test'
